visfer/__init__.py
visfer/__main__.py
visfer/main.py
visfer-0.1.0.dist-info/METADATA
visfer-0.1.0.dist-info/WHEEL
visfer-0.1.0.dist-info/entry_points.txt
visfer-0.1.0.dist-info/RECORD
